matrex/__init__.py
matrex/msro.py
matrex-0.0.1.dist-info/METADATA
matrex-0.0.1.dist-info/WHEEL
matrex-0.0.1.dist-info/licenses/LICENSE
matrex-0.0.1.dist-info/RECORD
