Metadata-Version: 2.1
Name: matrex
Version: 0.0.1
Summary: A package grouping matrices row reordering algorithms to minimize their front size.
Project-URL: Homepage, https://github.com/benjaminlanthier/matrex
Project-URL: Bug Tracker, https://github.com/benjaminlanthier/matrex/issues
Author-email: benjaminlanthier <benjamin.lanthier2@usherbrooke.ca>, cotejer <jeremy.cote6@usherbrooke.ca>
License-File: LICENSE
Classifier: License :: OSI Approved :: MIT License
Classifier: Operating System :: OS Independent
Classifier: Programming Language :: Python :: 3
Requires-Python: >=3.8
